README.md
pyproject.toml
setup.py
tmp_aiogram/__init__.py
tmp_aiogram/bot.py
tmp_aiogram/cli.py
tmp_aiogram/loader.py
tmp_aiogram.egg-info/PKG-INFO
tmp_aiogram.egg-info/SOURCES.txt
tmp_aiogram.egg-info/dependency_links.txt
tmp_aiogram.egg-info/entry_points.txt
tmp_aiogram.egg-info/requires.txt
tmp_aiogram.egg-info/top_level.txt
tmp_aiogram/handlers/__init__.py
tmp_aiogram/handlers/start.py
tmp_aiogram/services/__init__.py
tmp_aiogram/services/services.py
tmp_aiogram/state/__init__.py
tmp_aiogram/state/state.py
tmp_aiogram/utils/__init__.py
tmp_aiogram/utils/buttons.py
tmp_aiogram/utils/env.py
tmp_aiogram/utils/texts.py