Metadata-Version: 2.4
Name: tmp-aiogram
Version: 0.1
Home-page: https://github.com/Husanjonazamov/tmp-aiogram
Author: Husanjon Azamov
Author-email: azamovhusanboy@gmail.com
Classifier: Programming Language :: Python :: 3
Classifier: License :: OSI Approved :: MIT License
Classifier: Operating System :: OS Independent
Requires-Dist: aiogram==2.2
Requires-Dist: requests
Requires-Dist: click
Requires-Dist: autoenv-tool
Dynamic: author
Dynamic: author-email
Dynamic: classifier
Dynamic: home-page
Dynamic: requires-dist
